setup.py
jira_extended/__init__.py
jira_extended/jira_extended.py
jira_extended.egg-info/PKG-INFO
jira_extended.egg-info/SOURCES.txt
jira_extended.egg-info/dependency_links.txt
jira_extended.egg-info/requires.txt
jira_extended.egg-info/top_level.txt