Metadata-Version: 1.1
Name: jira-extended
Version: 0.1.2
Summary: Module that extends jira with additional functionality
Home-page: https://github.com/gillarkod/jira_extended
Author: marhag87
Author-email: marhag87@gmail.com
License: MIT
Platform: UNKNOWN
Classifier: Development Status :: 4 - Beta
Classifier: Intended Audience :: Developers
Classifier: Programming Language :: Python :: 3
